GPSconverter/__init__.py
GPSconverter/__main__.py
GPSconverter/DATA/LOGO.gif
GPSconverter-0.0.17.dist-info/LICENSE
GPSconverter-0.0.17.dist-info/METADATA
GPSconverter-0.0.17.dist-info/WHEEL
GPSconverter-0.0.17.dist-info/entry_points.txt
GPSconverter-0.0.17.dist-info/top_level.txt
GPSconverter-0.0.17.dist-info/RECORD
