Metadata-Version: 2.1
Name: GPSconverter
Version: 0.0.17
Summary: Python package for manipulating gps data and easily convert them to other different formats.
Home-page: https://github.com/carmelosammarco/GPSconverter
Author: Carmelo Sammarco
Author-email: sammarcocarmelo@gmail.com
License: gpl-3.0
Platform: OS Independent
Classifier: Development Status :: 3 - Alpha
Classifier: Intended Audience :: Science/Research
Classifier: Topic :: Scientific/Engineering
Classifier: Programming Language :: Python :: 3.8
Requires-Python: ~=3.6
Requires-Dist: gpxpy (>=1.4.0)
Requires-Dist: numpy (>=1.18.1)
Requires-Dist: pandas (>=1.0.3)
Requires-Dist: scipy (>=1.4.1)
Requires-Dist: folium (>=0.12.1)
Requires-Dist: Flask (>=2.0.1)
Requires-Dist: Pillow (>=8.2.0)
Requires-Dist: simplekml (>=1.3.5)
Requires-Dist: tkmacosx (>=1.0.3)
Requires-Dist: html2image (>=1.1.3)
Requires-Dist: pyshp (>=2.1.3)
Requires-Dist: matplotlib (>=3.4.2)
Requires-Dist: pygmt
